{
  "field_for_sorting": "выбрало", 
  "header": {
    "forms": [
      {
        "style": [], 
        "ana": "", 
        "content": "Вы́брало", 
        "place": [], 
        "type": "lemma", 
        "normalized_content": "выбрало"
      }
    ], 
    "style": [], 
    "place": [], 
    "pos": ""
  }, 
  "senses": [
    {
      "elements": [
        {
          "content": "констатация человеком сильной усталости, состояния, когда его стали покидать силы или терпение кончилось. Слово передает не только физическую усталость, но и моральную (от физической (монотонной) работы, ходьбы (например, по лесу) и т. д.).", 
          "tag": "def"
        }, 
        {
          "content": "Вы́брало из сил", 
          "translation": "очень устал.", 
          "tag": "example", 
          "bibl": "", 
          "normalized_content": "выбрало из сил"
        }, 
        {
          "content": "Всего вы́брало из сил, не могу больше итти. Из лихоте́нья вы́брало", 
          "translation": "все надоело.", 
          "tag": "example", 
          "bibl": "", 
          "normalized_content": "всего выбрало из сил, не могу больше итти. из лихотенья выбрало"
        }, 
        {
          "content": "Вы́брало меня терпеть его вы́ходки, пусть живёт отдельно.", 
          "translation": "", 
          "tag": "example", 
          "bibl": "", 
          "normalized_content": "выбрало меня терпеть его выходки, пусть живет отдельно."
        }
      ], 
      "n": "1"
    }
  ], 
  "type": "word", 
  "class": 1
}