{
  "field_for_sorting": "дониткисмокнуть", 
  "header": {
    "forms": [
      {
        "style": [], 
        "ana": "", 
        "content": "До ни́тки смо́кнуть", 
        "place": [], 
        "type": "lemma", 
        "normalized_content": "до нитки смокнуть"
      }
    ], 
    "style": [], 
    "place": [], 
    "pos": ""
  }, 
  "senses": [
    {
      "elements": [
        {
          "content": "промокнуть насквозь.", 
          "tag": "def"
        }
      ], 
      "n": "1"
    }
  ], 
  "type": "word", 
  "class": 3
}