{
  "field_for_sorting": "бисикозлят!", 
  "header": {
    "forms": [
      {
        "style": [], 
        "ana": "", 
        "content": "Би́си ко́злят!", 
        "place": [], 
        "type": "lemma", 
        "normalized_content": "биси козлят!"
      }
    ], 
    "style": [], 
    "place": [], 
    "pos": ""
  }, 
  "senses": [
    {
      "elements": [
        {
          "content": "говорили о неусидчивом, вертлявом, нетерпеливом человеке.", 
          "tag": "def"
        }, 
        {
          "content": "Тебя що, биси ко́злят!?", 
          "translation": "успокойся, не бесись, не суетись, чего ты бесишься.", 
          "tag": "example", 
          "bibl": "", 
          "normalized_content": "тебя що, биси козлят!?"
        }, 
        {
          "content": "Тебя шо биси ты́чут!?", 
          "translation": "", 
          "tag": "example", 
          "bibl": "", 
          "normalized_content": "тебя шо биси тычут!?"
        }, 
        {
          "style": [], 
          "ana": "Ср.", 
          "content": "би́си", 
          "tag": "ref", 
          "place": [], 
          "normalized_content": "биси"
        }
      ], 
      "n": "1"
    }
  ], 
  "type": "word", 
  "class": 0
}