{
  "field_for_sorting": "изгноить", 
  "header": {
    "forms": [
      {
        "style": [], 
        "ana": "", 
        "content": "Изгнои́ть", 
        "place": [], 
        "type": "lemma", 
        "normalized_content": "изгноить"
      }
    ], 
    "style": [], 
    "place": [], 
    "pos": ""
  }, 
  "senses": [
    {
      "elements": [
        {
          "content": "испортить, дать возможность сгнить чему-либо.", 
          "tag": "def"
        }, 
        {
          "content": "Сейгод много сена изгнои́ли. Всю зиму ка́танцы не сушили, дак все изгнои́ли.", 
          "translation": "", 
          "tag": "example", 
          "bibl": "", 
          "normalized_content": "сейгод много сена изгноили. всю зиму катанцы не сушили, дак все изгноили."
        }
      ], 
      "n": "1"
    }
  ], 
  "type": "word", 
  "class": 5
}