{
  "field_for_sorting": "набрать", 
  "header": {
    "forms": [
      {
        "style": [], 
        "ana": "", 
        "content": "Набра́ть", 
        "place": [], 
        "type": "lemma", 
        "normalized_content": "набрать"
      }, 
      {
        "style": [], 
        "ana": "несов.", 
        "content": "набира́ть", 
        "place": [], 
        "type": "inflected", 
        "normalized_content": "набирать"
      }
    ], 
    "style": [], 
    "place": [], 
    "pos": ""
  }, 
  "senses": [
    {
      "elements": [
        {
          "content": "насобирать ягод, грибов.", 
          "tag": "def"
        }, 
        {
          "style": [], 
          "ana": "Также –", 
          "content": "насбира́ть", 
          "tag": "ref", 
          "place": [], 
          "normalized_content": "насбирать"
        }, 
        {
          "content": "и", 
          "tag": "def"
        }, 
        {
          "style": [], 
          "ana": "многокр.", 
          "content": "насби́рывать", 
          "tag": "form", 
          "place": [], 
          "type": "inflected", 
          "normalized_content": "насбирывать"
        }, 
        {
          "style": [], 
          "ana": "многокр.", 
          "content": "насоби́рывать", 
          "tag": "form", 
          "place": [], 
          "type": "inflected", 
          "normalized_content": "насобирывать"
        }, 
        {
          "content": "За день три зобеньки брусницы насоби́рываю.", 
          "translation": "", 
          "tag": "example", 
          "bibl": "", 
          "normalized_content": "за день три зобеньки брусницы насобирываю."
        }
      ], 
      "n": "1"
    }, 
    {
      "elements": [
        {
          "content": "приобретать.", 
          "tag": "def"
        }, 
        {
          "content": "Не надо было стоко грибов преников набира́ть, вот денёг-то и не хватаёт!", 
          "translation": "(бабушка внуку).", 
          "tag": "example", 
          "bibl": "", 
          "normalized_content": "не надо было стоко грибов преников набирать, вот денег-то и не хватает!"
        }
      ], 
      "n": "2"
    }, 
    {
      "elements": [
        {
          "content": "взять много чего-либо в руки одновременно.", 
          "tag": "def"
        }, 
        {
          "content": "В ладо́шку стоко ягод набра́л, вот и просы́пал", 
          "translation": "(ребенку).", 
          "tag": "example", 
          "bibl": "", 
          "normalized_content": "в ладошку стоко ягод набрал, вот и просыпал"
        }, 
        {
          "style": [], 
          "ana": "См.", 
          "content": "брать", 
          "tag": "ref", 
          "place": [], 
          "normalized_content": "брать"
        }
      ], 
      "n": "3"
    }
  ], 
  "type": "word", 
  "class": 7
}