{
  "field_for_sorting": "ногавицы", 
  "header": {
    "forms": [
      {
        "style": [], 
        "ana": "", 
        "content": "Ногави́цы", 
        "place": [], 
        "type": "lemma", 
        "normalized_content": "ногавицы"
      }, 
      {
        "style": [], 
        "ana": "", 
        "content": "ногови́цы", 
        "place": [], 
        "type": "variant", 
        "normalized_content": "ноговицы"
      }
    ], 
    "style": [], 
    "place": [], 
    "pos": ""
  }, 
  "senses": [
    {
      "elements": [
        {
          "content": "шитые, иногда вязаные женские получулки, закрепленные у колена подвязкой, чаще их шили без следка (наподобие краг).", 
          "tag": "def"
        }
      ], 
      "n": "1"
    }
  ], 
  "type": "word", 
  "class": 8
}