{
  "field_for_sorting": "обрешетка", 
  "header": {
    "forms": [
      {
        "style": [], 
        "ana": "", 
        "content": "Обрешё́тка", 
        "place": [], 
        "type": "lemma", 
        "normalized_content": "обрешетка"
      }
    ], 
    "style": [], 
    "place": [], 
    "pos": ""
  }, 
  "senses": [
    {
      "elements": [
        {
          "content": "конструкция из реек или досок с промежутками между ними в виде решетки для настила по ней кровельных материалов на крышах. Используется также как специальная основа и каркас для сооружений, заборов, перегородок, ограждений и других подобных конструкций.", 
          "tag": "def"
        }
      ], 
      "n": "1"
    }
  ], 
  "type": "word", 
  "class": 8
}