{
  "field_for_sorting": "осиновка", 
  "header": {
    "forms": [
      {
        "style": [], 
        "ana": "", 
        "content": "Оси́новка", 
        "place": [], 
        "type": "lemma", 
        "normalized_content": "осиновка"
      }
    ], 
    "style": [], 
    "place": [], 
    "pos": ""
  }, 
  "senses": [
    {
      "elements": [
        {
          "content": "лодка, изготовленная из осины, путем выдалбливания и последующей разводки при помощи горячей воды.", 
          "tag": "def"
        }, 
        {
          "content": "Ло́́́тка-оси́́́нофка у и́́́х стари́́́нная, ещо де́́́довой робо́́́ты.", 
          "translation": "", 
          "tag": "example", 
          "bibl": "", 
          "normalized_content": "лотка-осинофка у их старинная, ещо дедовой роботы."
        }
      ], 
      "n": "1"
    }
  ], 
  "type": "word", 
  "class": 8
}