{
  "field_for_sorting": "подклеть", 
  "header": {
    "forms": [
      {
        "style": [], 
        "ana": "", 
        "content": "Подкле́ть", 
        "place": [], 
        "type": "lemma", 
        "normalized_content": "подклеть"
      }, 
      {
        "style": [], 
        "ana": "", 
        "content": "подкли́ть", 
        "place": [], 
        "type": "variant", 
        "normalized_content": "подклить"
      }, 
      {
        "style": [], 
        "ana": "", 
        "content": "подкле́́́т", 
        "place": [], 
        "type": "variant", 
        "normalized_content": "подклет"
      }, 
      {
        "style": [], 
        "ana": "", 
        "content": "подкли́́́т", 
        "place": [], 
        "type": "variant", 
        "normalized_content": "подклит"
      }, 
      {
        "style": [], 
        "ana": "", 
        "content": "покле́́́т", 
        "place": [], 
        "type": "variant", 
        "normalized_content": "поклет"
      }, 
      {
        "style": [], 
        "ana": "", 
        "content": "покли́́́т", 
        "place": [], 
        "type": "variant", 
        "normalized_content": "поклит"
      }
    ], 
    "style": [], 
    "place": [], 
    "pos": ""
  }, 
  "senses": [
    {
      "elements": [
        {
          "content": "в деревенском доме помещение под", 
          "tag": "def"
        }, 
        {
          "content": "кле́тью", 
          "tag": "quote", 
          "normalized_content": "клетью"
        }, 
        {
          "content": ", предназначенное для хранения продуктов (муки, мяса и т. п.).", 
          "tag": "def"
        }, 
        {
          "content": "Клеть", 
          "translation": "этот домик, а под ним в", 
          "tag": "example", 
          "bibl": "", 
          "normalized_content": "клеть"
        }, 
        {
          "content": "подкле́ти – ле́дник", 
          "tag": "quote", 
          "normalized_content": "подклети – ледник"
        }
      ], 
      "n": "1"
    }
  ], 
  "type": "word", 
  "class": 10
}