{
  "field_for_sorting": "придуриваться", 
  "header": {
    "forms": [
      {
        "style": [], 
        "ana": "", 
        "content": "Приду́риваться", 
        "place": [], 
        "type": "lemma", 
        "normalized_content": "придуриваться"
      }, 
      {
        "style": [], 
        "ana": "", 
        "content": "придуря́́́ться", 
        "place": [], 
        "type": "variant", 
        "normalized_content": "придуряться"
      }
    ], 
    "style": [], 
    "place": [], 
    "pos": ""
  }, 
  "senses": [
    {
      "elements": [
        {
          "content": "шалить, дурачиться, притворяться (", 
          "tag": "def"
        }, 
        {
          "style": [], 
          "ana": "сов.", 
          "content": "заприду́риваться", 
          "tag": "form", 
          "place": [], 
          "type": "inflected", 
          "normalized_content": "запридуриваться"
        }, 
        {
          "style": [], 
          "ana": "сов.", 
          "content": "наприду́риваться", 
          "tag": "form", 
          "place": [], 
          "type": "inflected", 
          "normalized_content": "напридуриваться"
        }, 
        {
          "style": [], 
          "ana": "сов.", 
          "content": "поприду́риваться", 
          "tag": "form", 
          "place": [], 
          "type": "inflected", 
          "normalized_content": "попридуриваться"
        }, 
        {
          "content": "Дава́́́й не приду́́́ривайсе – гляде́́́ть то́́́шно! Хва́́́тит придуря́́́тьце-то, как бу́́́тто мы тебя не зна́́́ём! Ох, оне севодни и поприду́ривались!", 
          "translation": "", 
          "tag": "example", 
          "bibl": "", 
          "normalized_content": "давай не придуривайсе – глядеть тошно! хватит придурятьце-то, как бутто мы тебя не знаем! ох, оне севодни и попридуривались!"
        }
      ], 
      "n": "1"
    }
  ], 
  "type": "word", 
  "class": 10
}