{
  "field_for_sorting": "прихвостень", 
  "header": {
    "forms": [
      {
        "style": [], 
        "ana": "", 
        "content": "При́хвостень", 
        "place": [], 
        "type": "lemma", 
        "normalized_content": "прихвостень"
      }
    ], 
    "style": [], 
    "place": [], 
    "pos": ""
  }, 
  "senses": [
    {
      "elements": [
        {
          "content": "пособник человека, обладающего властью и влиянием, притесняющего других.", 
          "tag": "def"
        }, 
        {
          "content": "У каждого тирана или хозяина находятся свои при́хвостни.", 
          "translation": "", 
          "tag": "example", 
          "bibl": "", 
          "normalized_content": "у каждого тирана или хозяина находятся свои прихвостни."
        }
      ], 
      "n": "1"
    }
  ], 
  "type": "word", 
  "class": 10
}