{
  "field_for_sorting": "пружить", 
  "header": {
    "forms": [
      {
        "style": [], 
        "ana": "", 
        "content": "Пру́жить", 
        "place": [], 
        "type": "lemma", 
        "normalized_content": "пружить"
      }
    ], 
    "style": [], 
    "place": [], 
    "pos": ""
  }, 
  "senses": [
    {
      "elements": [
        {
          "content": "валить, опрокидывать (", 
          "tag": "def"
        }, 
        {
          "style": [], 
          "ana": "сов.", 
          "content": "запру́жить", 
          "tag": "form", 
          "place": [], 
          "type": "inflected", 
          "normalized_content": "запружить"
        }, 
        {
          "style": [], 
          "ana": "сов.", 
          "content": "опру́жить", 
          "tag": "form", 
          "place": [], 
          "type": "inflected", 
          "normalized_content": "опружить"
        }, 
        {
          "style": [], 
          "ana": "сов.", 
          "content": "перепру́жить", 
          "tag": "form", 
          "place": [], 
          "type": "inflected", 
          "normalized_content": "перепружить"
        }, 
        {
          "content": "Пру́́́жь-ко скори́́́е вё́́́дра да пойдё́́́м ця́́́ю пи́́́ть. Надо эту яму чем-то запру́жить", 
          "translation": "завалить.", 
          "tag": "example", 
          "bibl": "", 
          "normalized_content": "пружь-ко скорие ведра да пойдем цяю пить. надо эту яму чем-то запружить"
        }, 
        {
          "content": "Воз на бок опру́жило.", 
          "translation": "", 
          "tag": "example", 
          "bibl": "", 
          "normalized_content": "воз на бок опружило."
        }
      ], 
      "n": "1"
    }, 
    {
      "elements": [
        {
          "content": "сбрасывать груз, сваливать опрокидыванием (", 
          "tag": "def"
        }, 
        {
          "style": [], 
          "ana": "сов.", 
          "content": "спру́жить", 
          "tag": "form", 
          "place": [], 
          "type": "inflected", 
          "normalized_content": "спружить"
        }, 
        {
          "style": [], 
          "ana": "несов.", 
          "content": "спру́живать", 
          "tag": "form", 
          "place": [], 
          "type": "inflected", 
          "normalized_content": "спруживать"
        }, 
        {
          "content": "Спруж сено вот тут.", 
          "translation": "", 
          "tag": "example", 
          "bibl": "", 
          "normalized_content": "спруж сено вот тут."
        }
      ], 
      "n": "2"
    }, 
    {
      "elements": [
        {
          "content": "приводить в напряженное состояние, натягивать (например, вожжи лошади).", 
          "tag": "def"
        }, 
        {
          "content": "Пружь лошадь-то, а то счас под угор с во́зом побежи́т!", 
          "translation": "натягивай вожжи сильнее, а то лошадь не остановишь!", 
          "tag": "example", 
          "bibl": "", 
          "normalized_content": "пружь лошадь-то, а то счас под угор с возом побежит!"
        }, 
        {
          "content": "Не надо лошадь сильно пру́жить, а то мешаёшь ей воз везти.", 
          "translation": "", 
          "tag": "example", 
          "bibl": "", 
          "normalized_content": "не надо лошадь сильно пружить, а то мешаешь ей воз везти."
        }, 
        {
          "style": [], 
          "ana": "Ср.", 
          "content": "распру́жить (лошадь)", 
          "tag": "ref", 
          "place": [], 
          "normalized_content": "распружить (лошадь)"
        }
      ], 
      "n": "3"
    }
  ], 
  "type": "word", 
  "class": 10
}