{
  "field_for_sorting": "пяла", 
  "header": {
    "forms": [
      {
        "style": [], 
        "ana": "", 
        "content": "Пя́ла", 
        "place": [], 
        "type": "lemma", 
        "normalized_content": "пяла"
      }
    ], 
    "style": [], 
    "place": [], 
    "pos": ""
  }, 
  "senses": [
    {
      "elements": [
        {
          "content": "изготовленное из жердей и досок наклонное устройство, устанавливаемое под крышей, предназначенное для сушки травы, веников с листьями, сырой одежды и др.", 
          "tag": "def"
        }
      ], 
      "n": "1"
    }
  ], 
  "type": "word", 
  "class": 11
}