{
  "field_for_sorting": "рвани", 
  "header": {
    "forms": [
      {
        "style": [], 
        "ana": "", 
        "content": "Рва́ни", 
        "place": [], 
        "type": "lemma", 
        "normalized_content": "рвани"
      }, 
      {
        "style": [], 
        "ana": "", 
        "content": "дать", 
        "place": [], 
        "type": "variant", 
        "normalized_content": "дать"
      }
    ], 
    "style": [], 
    "place": [], 
    "pos": ""
  }, 
  "senses": [
    {
      "elements": [
        {
          "content": "принять меры воспитательного воздействия: отругать или даже побить.", 
          "tag": "def"
        }, 
        {
          "content": "Ну родители нам и дадут рва́ни за то, что сильно провини́лись.", 
          "translation": "", 
          "tag": "example", 
          "bibl": "", 
          "normalized_content": "ну родители нам и дадут рвани за то, что сильно провинились."
        }
      ], 
      "n": "1"
    }
  ], 
  "type": "word", 
  "class": 11
}