{
  "field_for_sorting": "севоднишный", 
  "header": {
    "forms": [
      {
        "style": [], 
        "ana": "", 
        "content": "Сево́днишный", 
        "place": [], 
        "type": "lemma", 
        "normalized_content": "севоднишный"
      }, 
      {
        "style": [], 
        "ana": "", 
        "content": "сё́днишный", 
        "place": [], 
        "type": "variant", 
        "normalized_content": "седнишный"
      }
    ], 
    "style": [], 
    "place": [], 
    "pos": ""
  }, 
  "senses": [
    {
      "elements": [
        {
          "content": "произведенный или купленный сегодня.", 
          "tag": "def"
        }, 
        {
          "content": "Сево́днишный хлеб.", 
          "translation": "", 
          "tag": "example", 
          "bibl": "", 
          "normalized_content": "севоднишный хлеб."
        }
      ], 
      "n": "1"
    }
  ], 
  "type": "word", 
  "class": 11
}