{
  "field_for_sorting": "трубить", 
  "header": {
    "forms": [
      {
        "style": [], 
        "ana": "", 
        "content": "Труби́ть", 
        "place": [], 
        "type": "lemma", 
        "normalized_content": "трубить"
      }
    ], 
    "style": [], 
    "place": [], 
    "pos": ""
  }, 
  "senses": [
    {
      "elements": [
        {
          "content": "заупрямиться лошади в упряжке, выходить из повиновения (", 
          "tag": "def"
        }, 
        {
          "style": [], 
          "ana": "сов.", 
          "content": "затруби́ть", 
          "tag": "form", 
          "place": [], 
          "type": "inflected", 
          "normalized_content": "затрубить"
        }, 
        {
          "style": [], 
          "ana": "сов.", 
          "content": "потруби́ть", 
          "tag": "form", 
          "place": [], 
          "type": "inflected", 
          "normalized_content": "потрубить"
        }, 
        {
          "style": [], 
          "ana": "сов.", 
          "content": "струби́ть", 
          "tag": "form", 
          "place": [], 
          "type": "inflected", 
          "normalized_content": "струбить"
        }, 
        {
          "content": "У Зимы́ была нехорошая привычка труби́ть в упряжке. Не подавайте этого коня подростку, он может затруби́ть. Синю́ха любила потруби́ть в оглоблях, особенно если управлял подросток. Кобыла струби́ла и ушла с возом к конюшне.", 
          "translation": "", 
          "tag": "example", 
          "bibl": "", 
          "normalized_content": "у зимы была нехорошая привычка трубить в упряжке. не подавайте этого коня подростку, он может затрубить. синюха любила потрубить в оглоблях, особенно если управлял подросток. кобыла струбила и ушла с возом к конюшне."
        }
      ], 
      "n": "1"
    }
  ], 
  "type": "word", 
  "class": 13
}