{
  "field_for_sorting": "холстина", 
  "header": {
    "forms": [
      {
        "style": [], 
        "ana": "", 
        "content": "Холсти́на", 
        "place": [], 
        "type": "lemma", 
        "normalized_content": "холстина"
      }
    ], 
    "style": [], 
    "place": [], 
    "pos": ""
  }, 
  "senses": [
    {
      "elements": [
        {
          "content": "домотканая простая, грубая, льняная ткань, толстое полотно, имеет сорта: льняной или полотно, пачесный или полульняной, изгребной, отрепный.", 
          "tag": "def"
        }, 
        {
          "style": [], 
          "ana": "Также –", 
          "content": "холст", 
          "tag": "ref", 
          "place": [], 
          "normalized_content": "холст"
        }, 
        {
          "content": ". Вытканные", 
          "tag": "def"
        }, 
        {
          "content": "холсты", 
          "tag": "quote", 
          "normalized_content": "холсты"
        }, 
        {
          "content": "женщины белили, расстилая по начавшему таять ранней весной снегу или отаве (вновь отрастающей после скашивания траве) осенью.", 
          "tag": "def"
        }, 
        {
          "content": "Хоўста́́́-та у мня запасено́́́ нема́́́ло.", 
          "translation": "", 
          "tag": "example", 
          "bibl": "", 
          "normalized_content": "хоуста-та у мня запасено немало."
        }
      ], 
      "n": "1"
    }, 
    {
      "elements": [
        {
          "content": "вообще легкая полотняная или бумажная ткань особого переплетения.", 
          "tag": "def"
        }
      ], 
      "n": "2"
    }, 
    {
      "elements": [
        {
          "content": "кусок холста определенного размера.", 
          "tag": "def"
        }, 
        {
          "content": "Да́́́й-ко ту хоўсти́́́ну-ту, дак прикро́́́ю ша́́́нёшки-то на столе́́́, пусь оддохну́́́т.", 
          "translation": "", 
          "tag": "example", 
          "bibl": "", 
          "normalized_content": "дай-ко ту хоустину-ту, дак прикрою шанешки-то на столе, пусь оддохнут."
        }
      ], 
      "n": "3"
    }
  ], 
  "type": "word", 
  "class": 14
}