{
  "field_for_sorting": "хоромцы", 
  "header": {
    "forms": [
      {
        "style": [], 
        "ana": "", 
        "content": "Хоро́мцы", 
        "place": [], 
        "type": "lemma", 
        "normalized_content": "хоромцы"
      }
    ], 
    "style": [], 
    "place": [], 
    "pos": ""
  }, 
  "senses": [
    {
      "elements": [
        {
          "content": "навес из коротких досок над воротами.", 
          "tag": "def"
        }, 
        {
          "content": "Во двор для скота делали двухстворчатые широкие ворота, в которые свободно заезжали на лошади с телегой. Над воротами устраивали навес из коротких досок, по местному «хоро́мцы». Под такой крышей кололи и укладывали дрова, изготовляли дровни, подсанки, бороны, тесали, строгали, ставили временно лошадь", 
          "translation": "", 
          "tag": "example", 
          "bibl": "Рукопись «Записки о родной деревне». И.Н. Кононов. 1993 г.", 
          "normalized_content": "во двор для скота делали двухстворчатые широкие ворота, в которые свободно заезжали на лошади с телегой. над воротами устраивали навес из коротких досок, по местному «хоромцы». под такой крышей кололи и укладывали дрова, изготовляли дровни, подсанки, бороны, тесали, строгали, ставили временно лошадь"
        }
      ], 
      "n": "1"
    }
  ], 
  "type": "word", 
  "class": 14
}