{
  "field_for_sorting": "хрушкой", 
  "header": {
    "forms": [
      {
        "style": [], 
        "ana": "", 
        "content": "Хру́́́шкой", 
        "place": [], 
        "type": "lemma", 
        "normalized_content": "хрушкой"
      }, 
      {
        "style": [], 
        "ana": "", 
        "content": "хрушко́й", 
        "place": [], 
        "type": "variant", 
        "normalized_content": "хрушкой"
      }, 
      {
        "style": [], 
        "ana": "", 
        "content": "крушко́й", 
        "place": [
          "Подосенова"
        ], 
        "type": "variant", 
        "normalized_content": "крушкой"
      }
    ], 
    "style": [], 
    "place": [], 
    "pos": ""
  }, 
  "senses": [
    {
      "elements": [
        {
          "content": "крупный.", 
          "tag": "def"
        }, 
        {
          "content": "Ныне картовь уродиласе хрушка́я. Хру́́́шкой лук обреза́́́й в одну́́́ корзи́́́ну, ме́́́ўкой – в другу́́́ю. Снег идёт крушко́й, по лаптю снежина.", 
          "translation": "", 
          "tag": "example", 
          "bibl": "", 
          "normalized_content": "ныне картовь уродиласе хрушкая. хрушкой лук обрезай в одну корзину, меукой – в другую. снег идет крушкой, по лаптю снежина."
        }
      ], 
      "n": "1"
    }
  ], 
  "type": "word", 
  "class": 14
}