{
  "field_for_sorting": "шти", 
  "header": {
    "forms": [
      {
        "style": [], 
        "ana": "", 
        "content": "Шти́", 
        "place": [], 
        "type": "lemma", 
        "normalized_content": "шти"
      }, 
      {
        "style": [], 
        "ana": "", 
        "content": "шши́", 
        "place": [], 
        "type": "variant", 
        "normalized_content": "шши"
      }, 
      {
        "style": [], 
        "ana": "", 
        "content": "шщи́́́", 
        "place": [], 
        "type": "variant", 
        "normalized_content": "шщи"
      }
    ], 
    "style": [], 
    "place": [], 
    "pos": ""
  }, 
  "senses": [
    {
      "elements": [
        {
          "content": "щи.", 
          "tag": "def"
        }, 
        {
          "content": "Налива́́́й-ко, ма́́́ти, шще́́́й, я привё́́́л товаришще́́́й!", 
          "translation": "", 
          "tag": "example", 
          "bibl": "", 
          "normalized_content": "наливай-ко, мати, шщей, я привел товаришщей!"
        }, 
        {
          "content": "Раньше «шти» (так у нас говорили) подавали на стол в общем большом блюде. А для папы делали небольшую поблажку, наливая отдельное блюдо, чтобы тот мог читать и обедать", 
          "translation": "", 
          "tag": "example", 
          "bibl": "(Татьяна Петровна Абрамова", 
          "normalized_content": "раньше «шти» (так у нас говорили) подавали на стол в общем большом блюде. а для папы делали небольшую поблажку, наливая отдельное блюдо, чтобы тот мог читать и обедать"
        }, 
        {
          "content": "Рогачёва", 
          "tag": "place"
        }, 
        {
          "content": "). Загадочная Кырканда. В.Ф. Антуфьев, 2015 г.", 
          "tag": "def"
        }
      ], 
      "n": "1"
    }
  ], 
  "type": "word", 
  "class": 14
}